{
  "sessionId": "session-1770671459045",
  "status": "completed",
  "startedAt": "2026-02-09T21:10:59.046479",
  "completedAt": "2026-02-09T22:26:56.801000",
  "runs": [
    {
      "id": "SMK-004-1770671459058",
      "item_id": "SMK-004",
      "item": {
        "id": "SMK-004",
        "target": "Broken pipe behavior: pipe JSON output into `head`/`grep` and ensure no panic / exit 0",
        "priority": "P1",
        "risk": "Medium",
        "status": "\u2610 Not Started",
        "tier": "Tier 0: Setup & Smoke (must pass before deeper testing)"
      },
      "status": "completed",
      "stage": "processing",
      "attempt": 0,
      "max_attempts": 4,
      "started_at": "2026-02-09T21:10:59.067766",
      "completed_at": "2026-02-09T21:14:04.818382",
      "duration_ms": 185750,
      "error": null,
      "pid": 27341,
      "run_dir": "/home/antonio/programming/Hivemind/24-hour-hivemind/runs/tier_0_setup_smoke_must_pass_before_deeper_testing/SMK-004",
      "log_path": "/home/antonio/programming/Hivemind/24-hour-hivemind/runs/tier_0_setup_smoke_must_pass_before_deeper_testing/SMK-004/results/agent-SMK-004-1770671459065.log",
      "output_length": 0
    },
    {
      "id": "SMK-005-1770671644822",
      "item_id": "SMK-005",
      "item": {
        "id": "SMK-005",
        "target": "Data-dir isolation: set `HIVEMIND_DATA_DIR` to run-local dir; ensure no state leaks to `~/.hivemind`",
        "priority": "P0",
        "risk": "High",
        "status": "\u2610 Not Started",
        "tier": "Tier 0: Setup & Smoke (must pass before deeper testing)"
      },
      "status": "completed",
      "stage": "processing",
      "attempt": 0,
      "max_attempts": 4,
      "started_at": "2026-02-09T21:14:04.831324",
      "completed_at": "2026-02-09T21:17:55.208339",
      "duration_ms": 230377,
      "error": null,
      "pid": 28442,
      "run_dir": "/home/antonio/programming/Hivemind/24-hour-hivemind/runs/tier_0_setup_smoke_must_pass_before_deeper_testing/SMK-005",
      "log_path": "/home/antonio/programming/Hivemind/24-hour-hivemind/runs/tier_0_setup_smoke_must_pass_before_deeper_testing/SMK-005/results/agent-SMK-005-1770671644829.log",
      "output_length": 0
    },
    {
      "id": "SMK-006-1770671875213",
      "item_id": "SMK-006",
      "item": {
        "id": "SMK-006",
        "target": "Fresh install UX: run with empty data dir and ensure errors are structured + actionable",
        "priority": "P1",
        "risk": "Medium",
        "status": "\u2610 Not Started",
        "tier": "Tier 0: Setup & Smoke (must pass before deeper testing)"
      },
      "status": "completed",
      "stage": "processing",
      "attempt": 0,
      "max_attempts": 4,
      "started_at": "2026-02-09T21:17:55.220870",
      "completed_at": "2026-02-09T21:23:55.991668",
      "duration_ms": 360770,
      "error": null,
      "pid": 29991,
      "run_dir": "/home/antonio/programming/Hivemind/24-hour-hivemind/runs/tier_0_setup_smoke_must_pass_before_deeper_testing/SMK-006",
      "log_path": "/home/antonio/programming/Hivemind/24-hour-hivemind/runs/tier_0_setup_smoke_must_pass_before_deeper_testing/SMK-006/results/agent-SMK-006-1770671875219.log",
      "output_length": 0
    },
    {
      "id": "PRJ-001-1770672236015",
      "item_id": "PRJ-001",
      "item": {
        "id": "PRJ-001",
        "target": "`project create` + `project list` + `project inspect` (table + json)",
        "priority": "P0",
        "risk": "High",
        "status": "\u2610 Not Started",
        "tier": "Tier 1: Projects & Repositories (core registry UX)"
      },
      "status": "completed",
      "stage": "processing",
      "attempt": 0,
      "max_attempts": 4,
      "started_at": "2026-02-09T21:23:56.060522",
      "completed_at": "2026-02-09T21:26:56.904526",
      "duration_ms": 180844,
      "error": null,
      "pid": 32039,
      "run_dir": "/home/antonio/programming/Hivemind/24-hour-hivemind/runs/tier_1_projects_repositories_core_registry_ux/PRJ-001",
      "log_path": "/home/antonio/programming/Hivemind/24-hour-hivemind/runs/tier_1_projects_repositories_core_registry_ux/PRJ-001/results/agent-PRJ-001-1770672236037.log",
      "output_length": 0
    },
    {
      "id": "PRJ-002-1770672416909",
      "item_id": "PRJ-002",
      "item": {
        "id": "PRJ-002",
        "target": "`project update` name/description; confirm changes persist across process restart",
        "priority": "P1",
        "risk": "Medium",
        "status": "\u2610 Not Started",
        "tier": "Tier 1: Projects & Repositories (core registry UX)"
      },
      "status": "completed",
      "stage": "processing",
      "attempt": 0,
      "max_attempts": 4,
      "started_at": "2026-02-09T21:26:56.918283",
      "completed_at": "2026-02-09T21:29:34.308865",
      "duration_ms": 157390,
      "error": null,
      "pid": 33229,
      "run_dir": "/home/antonio/programming/Hivemind/24-hour-hivemind/runs/tier_1_projects_repositories_core_registry_ux/PRJ-002",
      "log_path": "/home/antonio/programming/Hivemind/24-hour-hivemind/runs/tier_1_projects_repositories_core_registry_ux/PRJ-002/results/agent-PRJ-002-1770672416916.log",
      "output_length": 0
    },
    {
      "id": "PRJ-003-1770672574322",
      "item_id": "PRJ-003",
      "item": {
        "id": "PRJ-003",
        "target": "`project attach-repo` to a sandbox git repo; inspect shows repo and access mode",
        "priority": "P0",
        "risk": "High",
        "status": "\u2610 Not Started",
        "tier": "Tier 1: Projects & Repositories (core registry UX)"
      },
      "status": "completed",
      "stage": "processing",
      "attempt": 0,
      "max_attempts": 4,
      "started_at": "2026-02-09T21:29:34.340846",
      "completed_at": "2026-02-09T21:32:55.758618",
      "duration_ms": 201417,
      "error": null,
      "pid": 35033,
      "run_dir": "/home/antonio/programming/Hivemind/24-hour-hivemind/runs/tier_1_projects_repositories_core_registry_ux/PRJ-003",
      "log_path": "/home/antonio/programming/Hivemind/24-hour-hivemind/runs/tier_1_projects_repositories_core_registry_ux/PRJ-003/results/agent-PRJ-003-1770672574331.log",
      "output_length": 0
    },
    {
      "id": "PRJ-004-1770672775760",
      "item_id": "PRJ-004",
      "item": {
        "id": "PRJ-004",
        "target": "`project attach-repo` invalid path: ensure structured Git/User error and non-zero exit code",
        "priority": "P0",
        "risk": "High",
        "status": "\u2610 Not Started",
        "tier": "Tier 1: Projects & Repositories (core registry UX)"
      },
      "status": "completed",
      "stage": "processing",
      "attempt": 0,
      "max_attempts": 4,
      "started_at": "2026-02-09T21:32:55.763717",
      "completed_at": "2026-02-09T21:37:10.110852",
      "duration_ms": 254347,
      "error": null,
      "pid": 36168,
      "run_dir": "/home/antonio/programming/Hivemind/24-hour-hivemind/runs/tier_1_projects_repositories_core_registry_ux/PRJ-004",
      "log_path": "/home/antonio/programming/Hivemind/24-hour-hivemind/runs/tier_1_projects_repositories_core_registry_ux/PRJ-004/results/agent-PRJ-004-1770672775762.log",
      "output_length": 0
    },
    {
      "id": "PRJ-005-1770673030112",
      "item_id": "PRJ-005",
      "item": {
        "id": "PRJ-005",
        "target": "`project attach-repo` non-git directory: ensure clear error + recovery hint",
        "priority": "P0",
        "risk": "High",
        "status": "\u2610 Not Started",
        "tier": "Tier 1: Projects & Repositories (core registry UX)"
      },
      "status": "completed",
      "stage": "processing",
      "attempt": 0,
      "max_attempts": 4,
      "started_at": "2026-02-09T21:37:10.116819",
      "completed_at": "2026-02-09T21:40:04.839398",
      "duration_ms": 174722,
      "error": null,
      "pid": 37559,
      "run_dir": "/home/antonio/programming/Hivemind/24-hour-hivemind/runs/tier_1_projects_repositories_core_registry_ux/PRJ-005",
      "log_path": "/home/antonio/programming/Hivemind/24-hour-hivemind/runs/tier_1_projects_repositories_core_registry_ux/PRJ-005/results/agent-PRJ-005-1770673030115.log",
      "output_length": 0
    },
    {
      "id": "PRJ-006-1770673204844",
      "item_id": "PRJ-006",
      "item": {
        "id": "PRJ-006",
        "target": "`project detach-repo` happy path + detach nonexistent repo (error classification)",
        "priority": "P1",
        "risk": "Medium",
        "status": "\u2610 Not Started",
        "tier": "Tier 1: Projects & Repositories (core registry UX)"
      },
      "status": "completed",
      "stage": "processing",
      "attempt": 0,
      "max_attempts": 4,
      "started_at": "2026-02-09T21:40:04.852312",
      "completed_at": "2026-02-09T21:43:19.401591",
      "duration_ms": 194549,
      "error": null,
      "pid": 38362,
      "run_dir": "/home/antonio/programming/Hivemind/24-hour-hivemind/runs/tier_1_projects_repositories_core_registry_ux/PRJ-006",
      "log_path": "/home/antonio/programming/Hivemind/24-hour-hivemind/runs/tier_1_projects_repositories_core_registry_ux/PRJ-006/results/agent-PRJ-006-1770673204850.log",
      "output_length": 0
    },
    {
      "id": "PRJ-007-1770673399403",
      "item_id": "PRJ-007",
      "item": {
        "id": "PRJ-007",
        "target": "`project runtime-set` minimal config; verify it is recorded (inspect + events)",
        "priority": "P0",
        "risk": "High",
        "status": "\u2610 Not Started",
        "tier": "Tier 1: Projects & Repositories (core registry UX)"
      },
      "status": "completed",
      "stage": "processing",
      "attempt": 0,
      "max_attempts": 4,
      "started_at": "2026-02-09T21:43:19.408491",
      "completed_at": "2026-02-09T21:47:44.707341",
      "duration_ms": 265298,
      "error": null,
      "pid": 39402,
      "run_dir": "/home/antonio/programming/Hivemind/24-hour-hivemind/runs/tier_1_projects_repositories_core_registry_ux/PRJ-007",
      "log_path": "/home/antonio/programming/Hivemind/24-hour-hivemind/runs/tier_1_projects_repositories_core_registry_ux/PRJ-007/results/agent-PRJ-007-1770673399407.log",
      "output_length": 0
    },
    {
      "id": "PRJ-008-1770673664709",
      "item_id": "PRJ-008",
      "item": {
        "id": "PRJ-008",
        "target": "`project runtime-set --env` parsing: invalid KEY=VALUE rejected with helpful error",
        "priority": "P1",
        "risk": "Medium",
        "status": "\u2610 Not Started",
        "tier": "Tier 1: Projects & Repositories (core registry UX)"
      },
      "status": "completed",
      "stage": "processing",
      "attempt": 0,
      "max_attempts": 4,
      "started_at": "2026-02-09T21:47:44.712559",
      "completed_at": "2026-02-09T21:50:54.143035",
      "duration_ms": 189430,
      "error": null,
      "pid": 40748,
      "run_dir": "/home/antonio/programming/Hivemind/24-hour-hivemind/runs/tier_1_projects_repositories_core_registry_ux/PRJ-008",
      "log_path": "/home/antonio/programming/Hivemind/24-hour-hivemind/runs/tier_1_projects_repositories_core_registry_ux/PRJ-008/results/agent-PRJ-008-1770673664711.log",
      "output_length": 0
    },
    {
      "id": "PRJ-009-1770673854145",
      "item_id": "PRJ-009",
      "item": {
        "id": "PRJ-009",
        "target": "Multi-project sanity: create 3 projects; ensure list/inspect always resolves correct project by name",
        "priority": "P2",
        "risk": "Low",
        "status": "\u2610 Not Started",
        "tier": "Tier 1: Projects & Repositories (core registry UX)"
      },
      "status": "completed",
      "stage": "processing",
      "attempt": 0,
      "max_attempts": 4,
      "started_at": "2026-02-09T21:50:54.149691",
      "completed_at": "2026-02-09T21:52:25.830035",
      "duration_ms": 91680,
      "error": null,
      "pid": 41699,
      "run_dir": "/home/antonio/programming/Hivemind/24-hour-hivemind/runs/tier_1_projects_repositories_core_registry_ux/PRJ-009",
      "log_path": "/home/antonio/programming/Hivemind/24-hour-hivemind/runs/tier_1_projects_repositories_core_registry_ux/PRJ-009/results/agent-PRJ-009-1770673854148.log",
      "output_length": 0
    },
    {
      "id": "TSK-001-1770673974353",
      "item_id": "TSK-001",
      "item": {
        "id": "TSK-001",
        "target": "`task create` with description; `task list --state`; `task inspect`",
        "priority": "P0",
        "risk": "High",
        "status": "\u2610 Not Started",
        "tier": "Tier 2: Tasks (CRUD + state constraints)"
      },
      "status": "completed",
      "stage": "processing",
      "attempt": 0,
      "max_attempts": 4,
      "started_at": "2026-02-09T21:52:54.357749",
      "completed_at": "2026-02-09T21:55:51.344783",
      "duration_ms": 176987,
      "error": null,
      "pid": 42337,
      "run_dir": "/home/antonio/programming/Hivemind/24-hour-hivemind/runs/tier_2_tasks_crud_state_constraints/TSK-001",
      "log_path": "/home/antonio/programming/Hivemind/24-hour-hivemind/runs/tier_2_tasks_crud_state_constraints/TSK-001/results/agent-TSK-001-1770673974357.log",
      "output_length": 0
    },
    {
      "id": "TSK-002-1770674151347",
      "item_id": "TSK-002",
      "item": {
        "id": "TSK-002",
        "target": "`task update` title/description; verify persisted across restart",
        "priority": "P2",
        "risk": "Low",
        "status": "\u2610 Not Started",
        "tier": "Tier 2: Tasks (CRUD + state constraints)"
      },
      "status": "completed",
      "stage": "processing",
      "attempt": 0,
      "max_attempts": 4,
      "started_at": "2026-02-09T21:55:51.350620",
      "completed_at": "2026-02-09T21:58:45.187219",
      "duration_ms": 173836,
      "error": null,
      "pid": 43165,
      "run_dir": "/home/antonio/programming/Hivemind/24-hour-hivemind/runs/tier_2_tasks_crud_state_constraints/TSK-002",
      "log_path": "/home/antonio/programming/Hivemind/24-hour-hivemind/runs/tier_2_tasks_crud_state_constraints/TSK-002/results/agent-TSK-002-1770674151349.log",
      "output_length": 0
    },
    {
      "id": "TSK-003-1770674325189",
      "item_id": "TSK-003",
      "item": {
        "id": "TSK-003",
        "target": "`task close` precondition: closing a task not in flow succeeds; closing twice is idempotent",
        "priority": "P1",
        "risk": "Medium",
        "status": "\u2610 Not Started",
        "tier": "Tier 2: Tasks (CRUD + state constraints)"
      },
      "status": "completed",
      "stage": "processing",
      "attempt": 0,
      "max_attempts": 4,
      "started_at": "2026-02-09T21:58:45.193299",
      "completed_at": "2026-02-09T22:03:43.952201",
      "duration_ms": 298758,
      "error": null,
      "pid": 44345,
      "run_dir": "/home/antonio/programming/Hivemind/24-hour-hivemind/runs/tier_2_tasks_crud_state_constraints/TSK-003",
      "log_path": "/home/antonio/programming/Hivemind/24-hour-hivemind/runs/tier_2_tasks_crud_state_constraints/TSK-003/results/agent-TSK-003-1770674325192.log",
      "output_length": 0
    },
    {
      "id": "TSK-004-1770674623955",
      "item_id": "TSK-004",
      "item": {
        "id": "TSK-004",
        "target": "`task close` in active flow must fail with a conflict error",
        "priority": "P0",
        "risk": "High",
        "status": "\u2610 Not Started",
        "tier": "Tier 2: Tasks (CRUD + state constraints)"
      },
      "status": "completed",
      "stage": "processing",
      "attempt": 0,
      "max_attempts": 4,
      "started_at": "2026-02-09T22:03:43.979038",
      "completed_at": "2026-02-09T22:07:55.784037",
      "duration_ms": 251804,
      "error": null,
      "pid": 45711,
      "run_dir": "/home/antonio/programming/Hivemind/24-hour-hivemind/runs/tier_2_tasks_crud_state_constraints/TSK-004",
      "log_path": "/home/antonio/programming/Hivemind/24-hour-hivemind/runs/tier_2_tasks_crud_state_constraints/TSK-004/results/agent-TSK-004-1770674623959.log",
      "output_length": 0
    },
    {
      "id": "TSK-005-1770674875786",
      "item_id": "TSK-005",
      "item": {
        "id": "TSK-005",
        "target": "Invalid `--scope` string is rejected (no panic); error includes hint and origin",
        "priority": "P1",
        "risk": "Medium",
        "status": "\u2610 Not Started",
        "tier": "Tier 2: Tasks (CRUD + state constraints)"
      },
      "status": "completed",
      "stage": "processing",
      "attempt": 0,
      "max_attempts": 4,
      "started_at": "2026-02-09T22:07:55.790443",
      "completed_at": "2026-02-09T22:12:36.217462",
      "duration_ms": 280427,
      "error": null,
      "pid": 46873,
      "run_dir": "/home/antonio/programming/Hivemind/24-hour-hivemind/runs/tier_2_tasks_crud_state_constraints/TSK-005",
      "log_path": "/home/antonio/programming/Hivemind/24-hour-hivemind/runs/tier_2_tasks_crud_state_constraints/TSK-005/results/agent-TSK-005-1770674875789.log",
      "output_length": 0
    },
    {
      "id": "TSK-006-1770675156220",
      "item_id": "TSK-006",
      "item": {
        "id": "TSK-006",
        "target": "Not-found errors: `task inspect <bad-id>` uses correct exit code and structured output",
        "priority": "P0",
        "risk": "High",
        "status": "\u2610 Not Started",
        "tier": "Tier 2: Tasks (CRUD + state constraints)"
      },
      "status": "completed",
      "stage": "processing",
      "attempt": 0,
      "max_attempts": 4,
      "started_at": "2026-02-09T22:12:36.230438",
      "completed_at": "2026-02-09T22:16:37.319229",
      "duration_ms": 241088,
      "error": null,
      "pid": 48505,
      "run_dir": "/home/antonio/programming/Hivemind/24-hour-hivemind/runs/tier_2_tasks_crud_state_constraints/TSK-006",
      "log_path": "/home/antonio/programming/Hivemind/24-hour-hivemind/runs/tier_2_tasks_crud_state_constraints/TSK-006/results/agent-TSK-006-1770675156229.log",
      "output_length": 0
    },
    {
      "id": "GRF-001-1770675438528",
      "item_id": "GRF-001",
      "item": {
        "id": "GRF-001",
        "target": "`graph create --from-tasks ...` and `graph validate` on a valid graph",
        "priority": "P0",
        "risk": "High",
        "status": "\u2610 Not Started",
        "tier": "Tier 3: Graph Planning (DAG semantics, idempotence, validation)"
      },
      "status": "completed",
      "stage": "processing",
      "attempt": 0,
      "max_attempts": 4,
      "started_at": "2026-02-09T22:17:18.540263",
      "completed_at": "2026-02-09T22:21:39.979127",
      "duration_ms": 261438,
      "error": null,
      "pid": 50264,
      "run_dir": "/home/antonio/programming/Hivemind/24-hour-hivemind/runs/tier_3_graph_planning_dag_semantics_idempotence_validation/GRF-001",
      "log_path": "/home/antonio/programming/Hivemind/24-hour-hivemind/runs/tier_3_graph_planning_dag_semantics_idempotence_validation/GRF-001/results/agent-GRF-001-1770675438539.log",
      "output_length": 0
    },
    {
      "id": "GRF-002-1770675699982",
      "item_id": "GRF-002",
      "item": {
        "id": "GRF-002",
        "target": "Dependency direction correctness: `add-dependency(from, to)` means **from depends on to**",
        "priority": "P0",
        "risk": "High",
        "status": "\u2610 Not Started",
        "tier": "Tier 3: Graph Planning (DAG semantics, idempotence, validation)"
      },
      "status": "completed",
      "stage": "processing",
      "attempt": 0,
      "max_attempts": 4,
      "started_at": "2026-02-09T22:21:39.991506",
      "completed_at": "2026-02-09T22:26:56.797107",
      "duration_ms": 316805,
      "error": null,
      "pid": 51528,
      "run_dir": "/home/antonio/programming/Hivemind/24-hour-hivemind/runs/tier_3_graph_planning_dag_semantics_idempotence_validation/GRF-002",
      "log_path": "/home/antonio/programming/Hivemind/24-hour-hivemind/runs/tier_3_graph_planning_dag_semantics_idempotence_validation/GRF-002/results/agent-GRF-002-1770675699990.log",
      "output_length": 0
    }
  ],
  "summary": {
    "session_id": "session-1770671459045",
    "status": "completed",
    "total": 20,
    "pending": 0,
    "active": 0,
    "completed": 20,
    "failed": 0,
    "timeout": 0
  }
}